napari_nasa_samples/__init__.py
napari_nasa_samples/_blue_marble.py
napari_nasa_samples/_hubble_lmc.py
napari_nasa_samples/_hubble_messier_101.py
napari_nasa_samples/_hubble_pillars_of_creation.py
napari_nasa_samples/_jwst_cosmic_cliffs.py
napari_nasa_samples/_jwst_smacs_0723.py
napari_nasa_samples/_jwst_southern_ring_nebula.py
napari_nasa_samples/_jwst_stephans_quintet.py
napari_nasa_samples/napari.yaml
napari_nasa_samples/utils.py
napari_nasa_samples/_tests/__init__.py
napari_nasa_samples/_tests/test_sample_data.py
napari_nasa_samples-0.0.5.dist-info/LICENSE
napari_nasa_samples-0.0.5.dist-info/METADATA
napari_nasa_samples-0.0.5.dist-info/WHEEL
napari_nasa_samples-0.0.5.dist-info/entry_points.txt
napari_nasa_samples-0.0.5.dist-info/top_level.txt
napari_nasa_samples-0.0.5.dist-info/RECORD
