Metadata-Version: 2.1
Name: napari-nasa-samples
Version: 0.0.5
Summary: This napari plugin provides sample datasets from NASA.
Home-page: https://github.com/royerloic/napari-nasa-samples
Author: Loic A. Royer
Author-email: royerloic@gmail.com
License: MPL-2.0
Project-URL: Bug Tracker, https://github.com/royerloic/napari-nasa-samples/issues
Project-URL: Documentation, https://github.com/royerloic/napari-nasa-samples#README.md
Project-URL: Source Code, https://github.com/royerloic/napari-nasa-samples
Project-URL: User Support, https://github.com/royerloic/napari-nasa-samples/issues
Classifier: Development Status :: 2 - Pre-Alpha
Classifier: Framework :: napari
Classifier: Intended Audience :: Developers
Classifier: License :: OSI Approved :: Mozilla Public License 2.0 (MPL 2.0)
Classifier: Operating System :: OS Independent
Classifier: Programming Language :: Python
Classifier: Programming Language :: Python :: 3
Classifier: Programming Language :: Python :: 3 :: Only
Classifier: Programming Language :: Python :: 3.8
Classifier: Programming Language :: Python :: 3.9
Classifier: Programming Language :: Python :: 3.10
Classifier: Topic :: Scientific/Engineering :: Image Processing
Requires-Python: >=3.8
License-File: LICENSE
Requires-Dist: numpy
Requires-Dist: requests
Requires-Dist: pillow
Provides-Extra: testing
Requires-Dist: tox ; extra == 'testing'
Requires-Dist: pytest ; extra == 'testing'
Requires-Dist: pytest-cov ; extra == 'testing'
